README.md
pubnubsubhandler.py
setup.cfg
setup.py
pubnubsub_handler.egg-info/PKG-INFO
pubnubsub_handler.egg-info/SOURCES.txt
pubnubsub_handler.egg-info/dependency_links.txt
pubnubsub_handler.egg-info/requires.txt
pubnubsub_handler.egg-info/top_level.txt
pubnubsub_handler.egg-info/zip-safe