Metadata-Version: 1.0
Name: pubnubsub-handler
Version: 1.0.7
Summary: Handles the PubNub subscriptions between PubNub and Home-Assistant for Wink
Home-page: https://github.com/w1ll1am23/pubnubsub-handler
Author: William Scanlon
Author-email: UNKNOWN
License: MIT
Platform: UNKNOWN
